pyfilehandling/__init__.py
pyfilehandling/customerrors.py
pyfilehandling/fileio.py
pyfilehandling/fileio.pyi
pyfilehandling/jsonfile.py
pyfilehandling/py.typed
pyfilehandling-3.2.1.dist-info/LICENSE.txt
pyfilehandling-3.2.1.dist-info/METADATA
pyfilehandling-3.2.1.dist-info/WHEEL
pyfilehandling-3.2.1.dist-info/RECORD
