Metadata-Version: 2.1
Name: pyfilehandling
Version: 3.2.1
Summary: A Python package for file manipulation operations.
Home-page: https://jeeldobariya38.github.io/PyFileHandling/
License: MIT
Keywords: file handling,file manipulation,file operation,utility
Author: Jeel Dobariya
Author-email: dobariyaj34@gmail.com
Requires-Python: >=3.9,<4.0
Classifier: Development Status :: 3 - Alpha
Classifier: Intended Audience :: Developers
Classifier: License :: OSI Approved :: MIT License
Classifier: Operating System :: OS Independent
Classifier: Programming Language :: Python
Classifier: Programming Language :: Python :: 3
Classifier: Programming Language :: Python :: 3.9
Classifier: Programming Language :: Python :: 3.10
Classifier: Programming Language :: Python :: 3.11
Classifier: Programming Language :: Python :: 3.12
Classifier: Topic :: Software Development :: Libraries :: Python Modules
Project-URL: Bug Tracker, https://github.com/JeelDobariya38/PyFileHandling/issues
Project-URL: Documentation, https://jeeldobariya38.github.io/PyFileHandling/pyfilehandling.html
Project-URL: Repository, https://github.com/JeelDobariya38/PyFileHandling
